UCpyR/__init__.py
UCpyR-0.1.dist-info/LICENSE.rtf
UCpyR-0.1.dist-info/METADATA
UCpyR-0.1.dist-info/WHEEL
UCpyR-0.1.dist-info/top_level.txt
UCpyR-0.1.dist-info/RECORD
